{"legislative_session": "2026rs", "identifier": "HB77", "title": "Taxation and Revenue; disabled veterans' homestead taxes inclusion in debt-to-income ratio under certain circumstances prohibited", "from_organization": "~{\"classification\": \"lower\"}", "classification": ["bill"], "subject": ["Taxation & Revenue"], "abstracts": [{"note": "full subject", "abstract": "Taxation & Revenue"}], "other_titles": [], "other_identifiers": [], "actions": [{"description": "Filed", "date": "2025-12-02T05:00:00+00:00", "organization_id": "~{\"classification\": \"lower\"}", "classification": ["filing"], "related_entities": []}, {"description": "Pending Committee Action in House of Origin (Military and Veterans' Affairs)", "date": "2026-01-13T05:00:00+00:00", "organization_id": "~{\"classification\": \"lower\"}", "classification": [], "related_entities": []}, {"description": "Read for the first time and referred to the House Committee on Military and Veterans' Affairs", "date": "2026-01-13T05:00:00+00:00", "organization_id": "~{\"classification\": \"lower\"}", "classification": ["reading-1", "referral-committee"], "related_entities": []}], "sponsorships": [{"name": "Paschal", "classification": "primary", "entity_type": "person", "primary": true, "person_id": "~{\"name\": \"Paschal\"}", "organization_id": null}], "related_bills": [], "versions": [{"note": "Introduced", "links": [{"url": "https://alison.legislature.state.al.us/files/pdf/SearchableInstruments/2026RS/HB77-int.pdf", "media_type": "application/pdf"}], "date": "", "classification": ""}], "documents": [], "citations": [], "sources": [{"url": "https://alison.legislature.state.al.us/bill-search", "note": ""}], "extras": {"AL_BILL_ID": "20868690"}, "jurisdiction": {"id": "ocd-jurisdiction/country:us/state:al/government", "name": "Alabama", "classification": "state", "division_id": "ocd-division/country:us/state:al"}, "scraped_at": "2025-12-10T21:40:46+00:00", "_id": "e2cbe8d0-d610-11f0-a1c6-ba9dbdef800c"}